ashishbansal_101703113_missing_value/__init__.py
ashishbansal_101703113_missing_value/missing_value.py
ashishbansal_101703113_missing_value-0.0.1.dist-info/LICENSE.txt
ashishbansal_101703113_missing_value-0.0.1.dist-info/METADATA
ashishbansal_101703113_missing_value-0.0.1.dist-info/WHEEL
ashishbansal_101703113_missing_value-0.0.1.dist-info/top_level.txt
ashishbansal_101703113_missing_value-0.0.1.dist-info/RECORD
