Metadata-Version: 2.1
Name: ashishbansal-101703113-missing-value
Version: 0.0.1
Summary: A small package that replaces missing values.
Home-page: UNKNOWN
Author: Ashish Bansal
Author-email: abansal2_be17@thapar.edu
License: UNKNOWN
Platform: UNKNOWN
Classifier: Programming Language :: Python :: 3
Classifier: License :: OSI Approved :: MIT License
Classifier: Operating System :: OS Independent
Requires-Python: >=3.6
